djandock/Dockerfile
djandock/__init__.py
djandock/__main__.py
djandock/add_git.py
djandock/django_proj.py
djandock/docker-compose.yml
djandock/docker_files.py
djandock/misc.py
djandock/presets.py
djandock/virtenv.py
djandock-1.6.0.dist-info/LICENSE
djandock-1.6.0.dist-info/METADATA
djandock-1.6.0.dist-info/WHEEL
djandock-1.6.0.dist-info/top_level.txt
djandock-1.6.0.dist-info/RECORD
