Metadata-Version: 2.1
Name: djandock
Version: 1.6.0
Summary: A simple utility to create Django projects with virtual environment, Git and Docker all set up
Home-page: https://github.com/marxygen/djandock
Author: marxygen
Author-email: marxygen@gmail.com
License: UNKNOWN
Project-URL: Bug Tracker, https://github.com/marxygen/djandock/issues
Platform: UNKNOWN
Classifier: Programming Language :: Python :: 3
Classifier: License :: OSI Approved :: MIT License
Classifier: Operating System :: OS Independent
Requires-Python: >=3.6
